{
  "directed": false,
  "multigraph": false,
  "graph": {},
  "nodes": [
    {
      "label": "logger.ts",
      "file_type": "code",
      "source_file": "logger.ts",
      "source_location": "L1",
      "_origin": "ast",
      "community": 0,
      "norm_label": "logger.ts",
      "id": "logger",
      "community_name": "Logging and Vendor Portal"
    },
    {
      "label": "logsDir",
      "file_type": "code",
      "source_file": "logger.ts",
      "source_location": "L5",
      "_origin": "ast",
      "community": 0,
      "norm_label": "logsdir",
      "id": "logger_logsdir",
      "community_name": "Logging and Vendor Portal"
    },
    {
      "label": "logger",
      "file_type": "code",
      "source_file": "logger.ts",
      "source_location": "L10",
      "_origin": "ast",
      "community": 0,
      "norm_label": "logger",
      "id": "logger_logger",
      "community_name": "Logging and Vendor Portal"
    },
    {
      "label": "validateBody.ts",
      "file_type": "code",
      "source_file": "middleware/validateBody.ts",
      "source_location": "L1",
      "_origin": "ast",
      "community": 2,
      "norm_label": "validatebody.ts",
      "id": "middleware_validatebody",
      "community_name": "validateBody.ts"
    },
    {
      "label": "validateBody()",
      "file_type": "code",
      "source_file": "middleware/validateBody.ts",
      "source_location": "L11",
      "_origin": "ast",
      "community": 3,
      "norm_label": "validatebody()",
      "id": "middleware_validatebody_validatebody",
      "community_name": "validateBody"
    },
    {
      "label": "agents.ts",
      "file_type": "code",
      "source_file": "routes/agents.ts",
      "source_location": "L1",
      "_origin": "ast",
      "community": 5,
      "norm_label": "agents.ts",
      "id": "routes_agents",
      "community_name": "agents.ts"
    },
    {
      "label": "agentsRouter",
      "file_type": "code",
      "source_file": "routes/agents.ts",
      "source_location": "L7",
      "_origin": "ast",
      "community": 5,
      "norm_label": "agentsrouter",
      "id": "routes_agents_agentsrouter",
      "community_name": "agents.ts"
    },
    {
      "label": "boq.ts",
      "file_type": "code",
      "source_file": "routes/boq.ts",
      "source_location": "L1",
      "_origin": "ast",
      "community": 4,
      "norm_label": "boq.ts",
      "id": "routes_boq",
      "community_name": "boq.ts"
    },
    {
      "label": "boqRouter",
      "file_type": "code",
      "source_file": "routes/boq.ts",
      "source_location": "L8",
      "_origin": "ast",
      "community": 4,
      "norm_label": "boqrouter",
      "id": "routes_boq_boqrouter",
      "community_name": "boq.ts"
    },
    {
      "label": "MockIngestSolution",
      "file_type": "code",
      "source_file": "routes/boq.ts",
      "source_location": "L16",
      "_origin": "ast",
      "community": 4,
      "norm_label": "mockingestsolution",
      "id": "routes_boq_mockingestsolution",
      "community_name": "boq.ts"
    },
    {
      "label": "health.ts",
      "file_type": "code",
      "source_file": "routes/health.ts",
      "source_location": "L1",
      "_origin": "ast",
      "community": 6,
      "norm_label": "health.ts",
      "id": "routes_health",
      "community_name": "health.ts"
    },
    {
      "label": "healthRouter",
      "file_type": "code",
      "source_file": "routes/health.ts",
      "source_location": "L3",
      "_origin": "ast",
      "community": 6,
      "norm_label": "healthrouter",
      "id": "routes_health_healthrouter",
      "community_name": "health.ts"
    },
    {
      "label": "jobs.ts",
      "file_type": "code",
      "source_file": "routes/jobs.ts",
      "source_location": "L1",
      "_origin": "ast",
      "community": 1,
      "norm_label": "jobs.ts",
      "id": "routes_jobs",
      "community_name": "Job Management"
    },
    {
      "label": "jobsRouter",
      "file_type": "code",
      "source_file": "routes/jobs.ts",
      "source_location": "L4",
      "_origin": "ast",
      "community": 1,
      "norm_label": "jobsrouter",
      "id": "routes_jobs_jobsrouter",
      "community_name": "Job Management"
    },
    {
      "label": "MockJob",
      "file_type": "code",
      "source_file": "routes/jobs.ts",
      "source_location": "L6",
      "_origin": "ast",
      "community": 1,
      "norm_label": "mockjob",
      "id": "routes_jobs_mockjob",
      "community_name": "Job Management"
    },
    {
      "label": "jobStore",
      "file_type": "code",
      "source_file": "routes/jobs.ts",
      "source_location": "L18",
      "_origin": "ast",
      "community": 1,
      "norm_label": "jobstore",
      "id": "routes_jobs_jobstore",
      "community_name": "Job Management"
    },
    {
      "label": "portfolio.ts",
      "file_type": "code",
      "source_file": "routes/portfolio.ts",
      "source_location": "L1",
      "_origin": "ast",
      "community": 2,
      "norm_label": "portfolio.ts",
      "id": "routes_portfolio",
      "community_name": "validateBody.ts"
    },
    {
      "label": "portfolioRouter",
      "file_type": "code",
      "source_file": "routes/portfolio.ts",
      "source_location": "L6",
      "_origin": "ast",
      "community": 2,
      "norm_label": "portfoliorouter",
      "id": "routes_portfolio_portfoliorouter",
      "community_name": "validateBody.ts"
    },
    {
      "label": "reconciliation.ts",
      "file_type": "code",
      "source_file": "routes/reconciliation.ts",
      "source_location": "L1",
      "_origin": "ast",
      "community": 3,
      "norm_label": "reconciliation.ts",
      "id": "routes_reconciliation",
      "community_name": "validateBody"
    },
    {
      "label": "reconciliationRouter",
      "file_type": "code",
      "source_file": "routes/reconciliation.ts",
      "source_location": "L8",
      "_origin": "ast",
      "community": 3,
      "norm_label": "reconciliationrouter",
      "id": "routes_reconciliation_reconciliationrouter",
      "community_name": "validateBody"
    },
    {
      "label": "snapshots.ts",
      "file_type": "code",
      "source_file": "routes/snapshots.ts",
      "source_location": "L1",
      "_origin": "ast",
      "community": 0,
      "norm_label": "snapshots.ts",
      "id": "routes_snapshots",
      "community_name": "Logging and Vendor Portal"
    },
    {
      "label": "snapshotsRouter",
      "file_type": "code",
      "source_file": "routes/snapshots.ts",
      "source_location": "L4",
      "_origin": "ast",
      "community": 0,
      "norm_label": "snapshotsrouter",
      "id": "routes_snapshots_snapshotsrouter",
      "community_name": "Logging and Vendor Portal"
    },
    {
      "label": "taxonomy.ts",
      "file_type": "code",
      "source_file": "routes/taxonomy.ts",
      "source_location": "L1",
      "_origin": "ast",
      "community": 7,
      "norm_label": "taxonomy.ts",
      "id": "routes_taxonomy",
      "community_name": "taxonomy.ts"
    },
    {
      "label": "taxonomyRouter",
      "file_type": "code",
      "source_file": "routes/taxonomy.ts",
      "source_location": "L7",
      "_origin": "ast",
      "community": 7,
      "norm_label": "taxonomyrouter",
      "id": "routes_taxonomy_taxonomyrouter",
      "community_name": "taxonomy.ts"
    },
    {
      "label": "vendorPortal.ts",
      "file_type": "code",
      "source_file": "routes/vendorPortal.ts",
      "source_location": "L1",
      "_origin": "ast",
      "community": 0,
      "norm_label": "vendorportal.ts",
      "id": "routes_vendorportal",
      "community_name": "Logging and Vendor Portal"
    },
    {
      "label": "vendorPortalRouter",
      "file_type": "code",
      "source_file": "routes/vendorPortal.ts",
      "source_location": "L6",
      "_origin": "ast",
      "community": 0,
      "norm_label": "vendorportalrouter",
      "id": "routes_vendorportal_vendorportalrouter",
      "community_name": "Logging and Vendor Portal"
    },
    {
      "label": "webhooks.ts",
      "file_type": "code",
      "source_file": "routes/webhooks.ts",
      "source_location": "L1",
      "_origin": "ast",
      "community": 8,
      "norm_label": "webhooks.ts",
      "id": "routes_webhooks",
      "community_name": "webhooks.ts"
    },
    {
      "label": "webhookRouter",
      "file_type": "code",
      "source_file": "routes/webhooks.ts",
      "source_location": "L7",
      "_origin": "ast",
      "community": 8,
      "norm_label": "webhookrouter",
      "id": "routes_webhooks_webhookrouter",
      "community_name": "webhooks.ts"
    }
  ],
  "links": [
    {
      "relation": "contains",
      "confidence": "EXTRACTED",
      "source_file": "logger.ts",
      "source_location": "L10",
      "weight": 1.0,
      "confidence_score": 1.0,
      "source": "logger",
      "target": "logger_logger"
    },
    {
      "relation": "contains",
      "confidence": "EXTRACTED",
      "source_file": "logger.ts",
      "source_location": "L5",
      "weight": 1.0,
      "confidence_score": 1.0,
      "source": "logger",
      "target": "logger_logsdir"
    },
    {
      "relation": "imports_from",
      "context": "import",
      "confidence": "EXTRACTED",
      "source_file": "routes/snapshots.ts",
      "source_location": "L2",
      "weight": 1.0,
      "confidence_score": 1.0,
      "source": "routes_snapshots",
      "target": "logger"
    },
    {
      "relation": "imports_from",
      "context": "import",
      "confidence": "EXTRACTED",
      "source_file": "routes/vendorPortal.ts",
      "source_location": "L4",
      "weight": 1.0,
      "confidence_score": 1.0,
      "source": "routes_vendorportal",
      "target": "logger"
    },
    {
      "relation": "imports",
      "context": "import",
      "confidence": "EXTRACTED",
      "source_file": "routes/snapshots.ts",
      "source_location": "L2",
      "weight": 1.0,
      "confidence_score": 1.0,
      "source": "routes_snapshots",
      "target": "logger_logger"
    },
    {
      "relation": "imports",
      "context": "import",
      "confidence": "EXTRACTED",
      "source_file": "routes/vendorPortal.ts",
      "source_location": "L4",
      "weight": 1.0,
      "confidence_score": 1.0,
      "source": "routes_vendorportal",
      "target": "logger_logger"
    },
    {
      "relation": "contains",
      "confidence": "EXTRACTED",
      "source_file": "middleware/validateBody.ts",
      "source_location": "L11",
      "weight": 1.0,
      "confidence_score": 1.0,
      "source": "middleware_validatebody",
      "target": "middleware_validatebody_validatebody"
    },
    {
      "relation": "imports_from",
      "context": "import",
      "confidence": "EXTRACTED",
      "source_file": "routes/agents.ts",
      "source_location": "L3",
      "weight": 1.0,
      "confidence_score": 1.0,
      "source": "routes_agents",
      "target": "middleware_validatebody"
    },
    {
      "relation": "imports_from",
      "context": "import",
      "confidence": "EXTRACTED",
      "source_file": "routes/boq.ts",
      "source_location": "L3",
      "weight": 1.0,
      "confidence_score": 1.0,
      "source": "routes_boq",
      "target": "middleware_validatebody"
    },
    {
      "relation": "imports_from",
      "context": "import",
      "confidence": "EXTRACTED",
      "source_file": "routes/portfolio.ts",
      "source_location": "L3",
      "weight": 1.0,
      "confidence_score": 1.0,
      "source": "routes_portfolio",
      "target": "middleware_validatebody"
    },
    {
      "relation": "imports_from",
      "context": "import",
      "confidence": "EXTRACTED",
      "source_file": "routes/reconciliation.ts",
      "source_location": "L3",
      "weight": 1.0,
      "confidence_score": 1.0,
      "source": "routes_reconciliation",
      "target": "middleware_validatebody"
    },
    {
      "relation": "imports_from",
      "context": "import",
      "confidence": "EXTRACTED",
      "source_file": "routes/taxonomy.ts",
      "source_location": "L2",
      "weight": 1.0,
      "confidence_score": 1.0,
      "source": "routes_taxonomy",
      "target": "middleware_validatebody"
    },
    {
      "relation": "imports_from",
      "context": "import",
      "confidence": "EXTRACTED",
      "source_file": "routes/vendorPortal.ts",
      "source_location": "L2",
      "weight": 1.0,
      "confidence_score": 1.0,
      "source": "routes_vendorportal",
      "target": "middleware_validatebody"
    },
    {
      "relation": "imports_from",
      "context": "import",
      "confidence": "EXTRACTED",
      "source_file": "routes/webhooks.ts",
      "source_location": "L3",
      "weight": 1.0,
      "confidence_score": 1.0,
      "source": "routes_webhooks",
      "target": "middleware_validatebody"
    },
    {
      "relation": "imports",
      "context": "import",
      "confidence": "EXTRACTED",
      "source_file": "routes/agents.ts",
      "source_location": "L3",
      "weight": 1.0,
      "confidence_score": 1.0,
      "source": "routes_agents",
      "target": "middleware_validatebody_validatebody"
    },
    {
      "relation": "imports",
      "context": "import",
      "confidence": "EXTRACTED",
      "source_file": "routes/boq.ts",
      "source_location": "L3",
      "weight": 1.0,
      "confidence_score": 1.0,
      "source": "routes_boq",
      "target": "middleware_validatebody_validatebody"
    },
    {
      "relation": "imports",
      "context": "import",
      "confidence": "EXTRACTED",
      "source_file": "routes/portfolio.ts",
      "source_location": "L3",
      "weight": 1.0,
      "confidence_score": 1.0,
      "source": "routes_portfolio",
      "target": "middleware_validatebody_validatebody"
    },
    {
      "relation": "imports",
      "context": "import",
      "confidence": "EXTRACTED",
      "source_file": "routes/reconciliation.ts",
      "source_location": "L3",
      "weight": 1.0,
      "confidence_score": 1.0,
      "source": "routes_reconciliation",
      "target": "middleware_validatebody_validatebody"
    },
    {
      "relation": "imports",
      "context": "import",
      "confidence": "EXTRACTED",
      "source_file": "routes/taxonomy.ts",
      "source_location": "L2",
      "weight": 1.0,
      "confidence_score": 1.0,
      "source": "routes_taxonomy",
      "target": "middleware_validatebody_validatebody"
    },
    {
      "relation": "imports",
      "context": "import",
      "confidence": "EXTRACTED",
      "source_file": "routes/vendorPortal.ts",
      "source_location": "L2",
      "weight": 1.0,
      "confidence_score": 1.0,
      "source": "routes_vendorportal",
      "target": "middleware_validatebody_validatebody"
    },
    {
      "relation": "imports",
      "context": "import",
      "confidence": "EXTRACTED",
      "source_file": "routes/webhooks.ts",
      "source_location": "L3",
      "weight": 1.0,
      "confidence_score": 1.0,
      "source": "routes_webhooks",
      "target": "middleware_validatebody_validatebody"
    },
    {
      "relation": "contains",
      "confidence": "EXTRACTED",
      "source_file": "routes/agents.ts",
      "source_location": "L7",
      "weight": 1.0,
      "confidence_score": 1.0,
      "source": "routes_agents",
      "target": "routes_agents_agentsrouter"
    },
    {
      "relation": "contains",
      "confidence": "EXTRACTED",
      "source_file": "routes/boq.ts",
      "source_location": "L8",
      "weight": 1.0,
      "confidence_score": 1.0,
      "source": "routes_boq",
      "target": "routes_boq_boqrouter"
    },
    {
      "relation": "contains",
      "confidence": "EXTRACTED",
      "source_file": "routes/boq.ts",
      "source_location": "L16",
      "weight": 1.0,
      "confidence_score": 1.0,
      "source": "routes_boq",
      "target": "routes_boq_mockingestsolution"
    },
    {
      "relation": "contains",
      "confidence": "EXTRACTED",
      "source_file": "routes/health.ts",
      "source_location": "L3",
      "weight": 1.0,
      "confidence_score": 1.0,
      "source": "routes_health",
      "target": "routes_health_healthrouter"
    },
    {
      "relation": "contains",
      "confidence": "EXTRACTED",
      "source_file": "routes/jobs.ts",
      "source_location": "L4",
      "weight": 1.0,
      "confidence_score": 1.0,
      "source": "routes_jobs",
      "target": "routes_jobs_jobsrouter"
    },
    {
      "relation": "contains",
      "confidence": "EXTRACTED",
      "source_file": "routes/jobs.ts",
      "source_location": "L18",
      "weight": 1.0,
      "confidence_score": 1.0,
      "source": "routes_jobs",
      "target": "routes_jobs_jobstore"
    },
    {
      "relation": "contains",
      "confidence": "EXTRACTED",
      "source_file": "routes/jobs.ts",
      "source_location": "L6",
      "weight": 1.0,
      "confidence_score": 1.0,
      "source": "routes_jobs",
      "target": "routes_jobs_mockjob"
    },
    {
      "relation": "contains",
      "confidence": "EXTRACTED",
      "source_file": "routes/portfolio.ts",
      "source_location": "L6",
      "weight": 1.0,
      "confidence_score": 1.0,
      "source": "routes_portfolio",
      "target": "routes_portfolio_portfoliorouter"
    },
    {
      "relation": "contains",
      "confidence": "EXTRACTED",
      "source_file": "routes/reconciliation.ts",
      "source_location": "L8",
      "weight": 1.0,
      "confidence_score": 1.0,
      "source": "routes_reconciliation",
      "target": "routes_reconciliation_reconciliationrouter"
    },
    {
      "relation": "contains",
      "confidence": "EXTRACTED",
      "source_file": "routes/snapshots.ts",
      "source_location": "L4",
      "weight": 1.0,
      "confidence_score": 1.0,
      "source": "routes_snapshots",
      "target": "routes_snapshots_snapshotsrouter"
    },
    {
      "relation": "contains",
      "confidence": "EXTRACTED",
      "source_file": "routes/taxonomy.ts",
      "source_location": "L7",
      "weight": 1.0,
      "confidence_score": 1.0,
      "source": "routes_taxonomy",
      "target": "routes_taxonomy_taxonomyrouter"
    },
    {
      "relation": "contains",
      "confidence": "EXTRACTED",
      "source_file": "routes/vendorPortal.ts",
      "source_location": "L6",
      "weight": 1.0,
      "confidence_score": 1.0,
      "source": "routes_vendorportal",
      "target": "routes_vendorportal_vendorportalrouter"
    },
    {
      "relation": "contains",
      "confidence": "EXTRACTED",
      "source_file": "routes/webhooks.ts",
      "source_location": "L7",
      "weight": 1.0,
      "confidence_score": 1.0,
      "source": "routes_webhooks",
      "target": "routes_webhooks_webhookrouter"
    }
  ],
  "hyperedges": [],
  "built_at_commit": "3436cdcc6d3c6caae6a8910325b1ae8dfe2c8864"
}